{
  "basics": {
    "name": "Manalu Nakanishi",
    "label": "Student",
    "picture": "https://manalun.github.io/images/Selfie(300px).jpg",
    "email": "manalun@hawaii.edu",
    "phone": "808-202-8627",
    "website": "https://manalun.github.io",
    "summary": "I am a student studying for a B.S. in Computer Science in the Department of Information and Computer Sciences at the University of Hawaii. I expect to graduate in Spring, 2022.",
    "location": {
      "address": "1293 Honokahua St",
      "postalCode": "96825",
      "city": "Honolulu",
      "countryCode": "USA",
      "region": "Hawaii"
    },
    "profiles": [
      {
        "network": "github",
        "username": "manalun",
        "url": "http://github.com/manalun"
      },
      {
        "network": "linkedin",
        "username": "mollymaluhia",
        "url": "http://linkedin.com/in/manalu-nakanishi-38068319b/"
      }
    ]
  },
  "interests": [
    {
      "name": "software engineering",
      "keywords": [
      ]
    },
    {
      "name": "game development",
      "keywords": [
      ]
    }
  ],
  "skills": [
    {
      "name": "Languages and Frameworks",
      "level": "",
      "keywords": [
        "C",
        "C++",
        "Java",
        "Javascript"
      ]
    },
    {
      "name": "Toolsets/OS",
      "level": "",
      "keywords": [
        "Git/GitHub"
      ]
    }
  ],
  "education": [
    {
      "institution": "University of Hawaii, Honolulu, HI",
      "area": "Computer Science (expected Spring, 2022)",
      "studyType": "B.S.",
      "startDate": "2018-08-12",
      "endDate": "Present",
      "gpa": "",
      "courses": [
      ]
    }
  ],
  "work": [
    {
      "company": "Outback Steakhouse",
      "position": "Take-away Server",
      "website": "https://www.outback.com/locations/hi/hawaii-kai",
      "startDate": "2018-02-01",
      "endDate": "Present",
      "summary": "Serve take-away orders for Outback Steakhouse.",
      "highlights": [
        "Multitask with taking orders, packing food and getting payment",
      ]
    },
    {
      "company": "Kozo Sushi",
      "position": "Sushi maker",
      "website": "",
      "startDate": "2016-03-01",
      "endDate": "2017-12-20",
      "summary": "Make sushi for customers and operate the cash register.",
      "highlights": [
        "Making sushi",
        "Maintain a clean working environment"      ]
    },
    {
      "company": "City and County of Honolulu",
      "position": "Summer Student Aide 2",
      "website": "http://www.honolulu.gov/parks/program/summer-fun-program.html",
      "startDate": "2019-05-30",
      "endDate": "2019-08-03",
      "summary": "Supervise and entertain 20+ kids for 6 hours.",
      "highlights": [
        "Figuring out activities that the kids would have fun with",
        "Working with coworkers to make the kids' summer awesome"      ]
    }
  ],
  "volunteer": [
    {
      "organization": "City and County of Honolulu",
      "website": "http://www.honolulu.gov/parks/program/summer-fun-program.html",
      "position": "Junior Leader",
      "startDate": "2016-06-01",
      "endDate": "2018-07-25",
      "summary": "Assist the Leaders supervise and entertain the group kids.",
      "highlights": [
        "Learn to complete tasks efficiently when assigned",
        "Cooperate with other junior leaders to help ease the work load for the leader"
      ]
    }
  ],
  "awards": [
    {
      "title": "Mānoa Academic Merit Scholarship",
      "date": "2018-Present",
      "awarder": "State of Hawaii",
      "summary": "This scholarship is for first-time, degree-seeking students who enroll the semester after high school graduation. The student must be enrolled in a full-time course load of UH Mānoa credits."
    },
    {
      "title": "Academic Excellence in Math",
      "date": "2013",
      "awarder": "Niu Valley Middle School",
      "summary": "Award given from nomination by a teacher for showing excellence in the subject of math."
    }
  ],
  "references": [
    {
      "name": "Available upon request",
      "reference": ""
    }
  ]
}
